aws_mfa_profiles/__init__.py
aws_mfa_profiles/__main__.py
aws_mfa_profiles-2.0.0.dist-info/METADATA
aws_mfa_profiles-2.0.0.dist-info/WHEEL
aws_mfa_profiles-2.0.0.dist-info/entry_points.txt
aws_mfa_profiles-2.0.0.dist-info/top_level.txt
aws_mfa_profiles-2.0.0.dist-info/RECORD
