Metadata-Version: 2.1
Name: aws-mfa-profiles
Version: 2.0.0
Summary: A package to create credential for AWS using MFA and with the support of multiple profiles
Home-page: https://github.com/lucapisciotta/aws-mfa-profiles
Author: Luca Pisciotta
Author-email: luca.pisciotta+pypi@live.it
License: MIT
Classifier: License :: OSI Approved :: MIT License
Classifier: Programming Language :: Python :: 3
Classifier: Programming Language :: Python :: 3.7
Classifier: Programming Language :: Python :: 3.8
Classifier: Programming Language :: Python :: 3.9
Classifier: Programming Language :: Python :: 3.10
Classifier: Development Status :: 5 - Production/Stable
Requires-Dist: boto3
Requires-Dist: inquirer
